simtradelab/AGENTS.md
simtradelab/__init__.py
simtradelab/backtest/__init__.py
simtradelab/backtest/config.py
simtradelab/backtest/optimizer_framework.py
simtradelab/backtest/run_backtest.py
simtradelab/backtest/runner.py
simtradelab/backtest/stats.py
simtradelab/backtest/stats_collector.py
simtradelab/cli/data_tools.py
simtradelab/ptrade/__init__.py
simtradelab/ptrade/adj_cache.py
simtradelab/ptrade/api.py
simtradelab/ptrade/cache_manager.py
simtradelab/ptrade/config_manager.py
simtradelab/ptrade/context.py
simtradelab/ptrade/data_context.py
simtradelab/ptrade/lifecycle_config.py
simtradelab/ptrade/lifecycle_controller.py
simtradelab/ptrade/object.py
simtradelab/ptrade/order_processor.py
simtradelab/ptrade/storage.py
simtradelab/ptrade/strategy_data_analyzer.py
simtradelab/ptrade/strategy_engine.py
simtradelab/ptrade/strategy_validator.py
simtradelab/research/api.py
simtradelab/research/notebook.ipynb
simtradelab/service/__init__.py
simtradelab/service/data_server.py
simtradelab/trading/todo.txt
simtradelab/utils/config.py
simtradelab/utils/fstring_fixer.py
simtradelab/utils/paths.py
simtradelab/utils/perf.py
simtradelab/utils/performance_config.py
simtradelab/utils/py35_compat_checker.py
simtradelab-2.1.0.dist-info/METADATA
simtradelab-2.1.0.dist-info/WHEEL
simtradelab-2.1.0.dist-info/licenses/LICENSE
simtradelab-2.1.0.dist-info/RECORD
