Metadata-Version: 2.4
Name: simtradelab
Version: 2.1.0
Summary: 开源策略回测框架，灵感来自PTrade的事件驱动模型，提供轻量、清晰、可插拔的策略验证环境
License: AGPL-3.0-or-later
License-File: LICENSE
Keywords: quantitative,backtest,trading,strategy,ptrade,finance
Author: kay
Author-email: kayou@duck.com
Requires-Python: >=3.9,<4.0
Classifier: Development Status :: 4 - Beta
Classifier: Intended Audience :: Developers
Classifier: Intended Audience :: Financial and Insurance Industry
Classifier: Intended Audience :: Science/Research
Classifier: License :: OSI Approved :: GNU Affero General Public License v3
Classifier: License :: OSI Approved :: GNU Affero General Public License v3 or later (AGPLv3+)
Classifier: License :: Other/Proprietary License
Classifier: Operating System :: OS Independent
Classifier: Programming Language :: Python :: 3
Classifier: Programming Language :: Python :: 3.9
Classifier: Programming Language :: Python :: 3.10
Classifier: Programming Language :: Python :: 3.11
Classifier: Programming Language :: Python :: 3.12
Classifier: Programming Language :: Python :: 3.13
Classifier: Programming Language :: Python :: 3.14
Classifier: Topic :: Office/Business :: Financial :: Investment
Classifier: Topic :: Scientific/Engineering :: Information Analysis
Provides-Extra: optimizer
Requires-Dist: cachetools (>=5.3.0,<6.0.0)
Requires-Dist: joblib (>=1.3.0,<2.0.0)
Requires-Dist: matplotlib (>=3.7.0,<4.0.0)
Requires-Dist: numpy (<2.0)
Requires-Dist: optuna (>=3.0.0,<4.0.0) ; extra == "optimizer"
Requires-Dist: pandas
Requires-Dist: pydantic (>=2.12.5,<3.0.0)
Requires-Dist: ta-lib
Requires-Dist: tqdm (>=4.67.1,<5.0.0)
Project-URL: Documentation, https://github.com/kay-ou/SimTradeLab/tree/main/docs
Project-URL: Homepage, https://github.com/kay-ou/SimTradeLab
Project-URL: Repository, https://github.com/kay-ou/SimTradeLab
